syct/__init__.py
syct/timer_module.py
syct-0.4.5.dist-info/LICENSE
syct-0.4.5.dist-info/METADATA
syct-0.4.5.dist-info/WHEEL
syct-0.4.5.dist-info/top_level.txt
syct-0.4.5.dist-info/RECORD
