Metadata-Version: 2.1
Name: syct
Version: 0.4.5
Summary: A Simple Yet Convenient Timer module for Python 3
Home-page: https://github.com/nadavo/Timer.git
Author: Nadav Oved
Author-email: nadavo@gmail.com
Classifier: Programming Language :: Python :: 3
Classifier: License :: OSI Approved :: MIT License
Classifier: Operating System :: OS Independent
Requires-Python: >=3
License-File: LICENSE
